asyncio_redis/__init__.py
asyncio_redis/connection.py
asyncio_redis/cursors.py
asyncio_redis/encoders.py
asyncio_redis/exceptions.py
asyncio_redis/log.py
asyncio_redis/pool.py
asyncio_redis/protocol.py
asyncio_redis/replies.py
asyncio_redis-0.16.0.dist-info/AUTHORS.rst
asyncio_redis-0.16.0.dist-info/LICENSE.txt
asyncio_redis-0.16.0.dist-info/METADATA
asyncio_redis-0.16.0.dist-info/WHEEL
asyncio_redis-0.16.0.dist-info/top_level.txt
asyncio_redis-0.16.0.dist-info/RECORD
