Metadata-Version: 2.1
Name: asyncio_redis
Version: 0.16.0
Summary: PEP 3156 implementation of the redis protocol.
Home-page: https://github.com/jonathanslenders/asyncio-redis
Author: Jonathan Slenders
License: LICENSE.txt
Platform: UNKNOWN
Classifier: Development Status :: 4 - Beta
Classifier: Framework :: AsyncIO
Classifier: Intended Audience :: Developers
Classifier: Topic :: Database
Classifier: Programming Language :: Python
Classifier: Programming Language :: Python :: 3 :: Only
Classifier: Programming Language :: Python :: 3.6
Classifier: Programming Language :: Python :: 3.7
Classifier: Programming Language :: Python :: 3.8
Requires-Python: >=3.6
Provides-Extra: hiredis
